integrationos/__init__.py
integrationos/auth_kit.py
integrationos_authkit-1.2.0.dist-info/LICENSE
integrationos_authkit-1.2.0.dist-info/METADATA
integrationos_authkit-1.2.0.dist-info/WHEEL
integrationos_authkit-1.2.0.dist-info/top_level.txt
integrationos_authkit-1.2.0.dist-info/RECORD
