Metadata-Version: 2.1
Name: integrationos-authkit
Version: 1.2.0
Summary: Secure token generation for IntegrationOS AuthKit in Python
Home-page: https://github.com/integration-os/authkit-python
Author: IntegrationOS
Author-email: dev@integrationos.com
Classifier: Development Status :: 3 - Alpha
Classifier: Intended Audience :: Developers
Classifier: License :: OSI Approved :: MIT License
Classifier: Operating System :: OS Independent
Classifier: Programming Language :: Python :: 3
Classifier: Programming Language :: Python :: 3.6
Classifier: Programming Language :: Python :: 3.7
Classifier: Programming Language :: Python :: 3.8
Classifier: Programming Language :: Python :: 3.9
Requires-Python: >=3.6
License-File: LICENSE
Requires-Dist: requests >=2.25.1
